droidmind/__init__.py
droidmind/adb.py
droidmind/client.py
droidmind/console.py
droidmind/context.py
droidmind/devices.py
droidmind/filesystem.py
droidmind/log.py
droidmind/packages.py
droidmind/prompts.py
droidmind/security.py
droidmind/server.py
droidmind/tools/__init__.py
droidmind/tools/app_management.py
droidmind/tools/common.py
droidmind/tools/device_management.py
droidmind/tools/diagnostics.py
droidmind/tools/file_operations.py
droidmind/tools/intents.py
droidmind/tools/logs.py
droidmind/tools/media.py
droidmind/tools/shell.py
droidmind/tools/ui.py
droidmind-0.4.0.dist-info/METADATA
droidmind-0.4.0.dist-info/WHEEL
droidmind-0.4.0.dist-info/entry_points.txt
droidmind-0.4.0.dist-info/licenses/LICENSE
droidmind-0.4.0.dist-info/RECORD
