Metadata-Version: 2.4
Name: droidmind
Version: 0.4.0
Summary: Control Android devices with MCP
Project-URL: Homepage, https://github.com/hyperb1iss/droidmind
Project-URL: Issues, https://github.com/hyperb1iss/droidmind/issues
Project-URL: Documentation, https://github.com/hyperb1iss/droidmind#readme
Author-email: Stefanie Jane <stef@hyperbliss.tech>
License:                                  Apache License
License-File: LICENSE
Keywords: ai,android,claude,llm,mcp
Classifier: Development Status :: 4 - Beta
Classifier: Intended Audience :: Developers
Classifier: License :: OSI Approved :: Apache Software License
Classifier: Programming Language :: Python :: 3
Classifier: Programming Language :: Python :: 3.13
Requires-Python: <3.14,>=3.13
Requires-Dist: aiofiles>=23.2.1
Requires-Dist: httpx>=0.28.1
Requires-Dist: mcp[cli]>=1.25.0
Requires-Dist: pillow>=11.2.1
Requires-Dist: rich-gradient>=0.2.0
Requires-Dist: rich>=14.0.0
Requires-Dist: sse-starlette>=2.3.5
Requires-Dist: starlette>=0.46.1
Requires-Dist: uvicorn>=0.34.2
